cli_intern/__init__.py
cli_intern/beauty_terminal/__init__.py
cli_intern/beauty_terminal/clean_terminal.py
cli_intern/beauty_terminal/text_line_decorator.py
cli_intern/organize_files/__init__.py
cli_intern/organize_files/create_file_structure_data_analysis.py
cli_intern-0.0.2.dist-info/LICENSE.md
cli_intern-0.0.2.dist-info/METADATA
cli_intern-0.0.2.dist-info/WHEEL
cli_intern-0.0.2.dist-info/top_level.txt
cli_intern-0.0.2.dist-info/RECORD
