Metadata-Version: 2.1
Name: cli-intern
Version: 0.0.2
Summary: A collection of utilities for command-line interfaces (CLIs) in Python.
Home-page: https://github.com/jonasaacampos/cli_utils
Author: jonasaacampos
Author-email: jonasaacampos@gmail.com
Requires-Python: >=3.0
License-File: LICENSE.md
